pyoui/__init__.py
pyoui/__main__.py
pyoui/oui.py
pyoui/py.typed
pyoui-1.1.1.dist-info/METADATA
pyoui-1.1.1.dist-info/WHEEL
pyoui-1.1.1.dist-info/entry_points.txt
pyoui-1.1.1.dist-info/licenses/LICENSE
pyoui-1.1.1.dist-info/RECORD
