Metadata-Version: 2.4
Name: pyoui
Version: 1.1.1
Summary: Lookup the IEEE's OUI table by MAC, MAC prefix, organization name, or country
Project-URL: Homepage, https://github.com/nbdy/pyoui
Project-URL: Issues, https://github.com/nbdy/pyoui/issues
Author-email: nbdy <me@nbdy.io>
License: MIT License
License-File: LICENSE
Keywords: lookup,mac,oui
Classifier: Development Status :: 3 - Alpha
Classifier: Intended Audience :: Developers
Classifier: License :: OSI Approved :: MIT License
Classifier: Programming Language :: Python :: 3
Classifier: Programming Language :: Python :: 3 :: Only
Classifier: Programming Language :: Python :: 3.7
Classifier: Topic :: Software Development :: Build Tools
Requires-Python: >=3.9
Requires-Dist: loguru==0.7.3
Requires-Dist: pycountry==24.6.1
Requires-Dist: requests==2.32.5
Requires-Dist: rich==14.2.0
Requires-Dist: tqdm==4.67.1
Provides-Extra: dev
Requires-Dist: pre-commit==4.3.0; extra == 'dev'
Requires-Dist: pytest==8.4.2; extra == 'dev'
Requires-Dist: ruff==0.14.13; extra == 'dev'
